<?xml version="1.0" encoding="UTF-8"?>
<resolvers>
    <resolver>
        
        <!--解析器的基本信息-->
        <basicInfo>
            <name>zaimanhua</name>
            <version>20250712_StupidDoll</version>
            <baseUrl>https://m.zaimanhua.com</baseUrl>
            <startUrl>https://m.zaimanhua.com/api/app/v1/comic/update/list/0/1</startUrl>
            <type>comic</type>
            <template>3</template>
            <access>Get</access>
            <charset>UTF-8</charset>
            <header>Referer*https://m.zaimanhua.com</header>
            <order>desc</order>
        </basicInfo>
        
        <!--查询规则-->
        <searchRule>
            <action>https://m.zaimanhua.com/api/app/v1/search/index?keyword=</action>
            <method>Get</method>
            <inputName>null</inputName>
            <inputFormatParam>null</inputFormatParam>
            <level>3</level>
            <targetLevel>1</targetLevel>
            <extraParam>&amp;source=0&amp;size=20&amp;page=1</extraParam>
            <isJoint>yes</isJoint>
            <captchaInfo>null</captchaInfo>
        </searchRule>
        
        <!--跳转规则-->
        <jumpRule>
            <method>mantissaIncrease</method>
            <parameter>null</parameter>
            <regular>https://m.zaimanhua.com.*</regular>
            <offset>null</offset>
            <startPage>null</startPage>
        </jumpRule>
        
        <!--底层导航栏-->
        <menuBar>
            <menu>
                <text>更新</text>
                <url>https://m.zaimanhua.com/api/app/v1/comic/update/list/0/1</url>
                <level>1</level>
                <css>1</css>
                <baseUrl>null</baseUrl>
                <regular>null</regular>
                <subset></subset>
            </menu>
            <menu>
                <text>blank</text>
                <url>null</url>
                <level>1</level>
                <css>2</css>
                <baseUrl>null</baseUrl>
                <regular>https://m.zaimanhua.com/api/app/v1/search/index\?keyword=.*</regular>
                <subset></subset>
            </menu>
            <menu>
                <text>分类</text>
                <url>null</url>
                <level>1</level>
                <css>3</css>
                <baseUrl>null</baseUrl>
                <regular>https://m.zaimanhua.com/api/app/v1/comic/filter/list.*</regular>
                <subset>
                    <submenu>
                        <text>魔法</text>
                        <url>https://m.zaimanhua.com/api/app/v1/comic/filter/list?status=0&amp;theme=11&amp;zone=0&amp;sortType=1&amp;size=20&amp;cate=0&amp;page=1</url>
                        <level>2</level>
                    </submenu>
                    <submenu>
                        <text>职场</text>
                        <url>https://m.zaimanhua.com/api/app/v1/comic/filter/list?status=0&amp;theme=3328&amp;zone=0&amp;sortType=1&amp;size=20&amp;cate=0&amp;page=1</url>
                        <level>2</level>
                    </submenu>
                    <submenu>
                        <text>治愈</text>
                        <url>https://m.zaimanhua.com/api/app/v1/comic/filter/list?status=0&amp;theme=3254&amp;zone=0&amp;sortType=1&amp;size=20&amp;cate=0&amp;page=1</url>
                        <level>2</level>
                    </submenu>
                    <submenu>
                        <text>萌系</text>
                        <url>https://m.zaimanhua.com/api/app/v1/comic/filter/list?status=0&amp;theme=3252&amp;zone=0&amp;sortType=1&amp;size=20&amp;cate=0&amp;page=1</url>
                        <level>2</level>
                    </submenu>
                    <submenu>
                        <text>轻改</text>
                        <url>https://m.zaimanhua.com/api/app/v1/comic/filter/list?status=0&amp;theme=6316&amp;zone=0&amp;sortType=1&amp;size=20&amp;cate=0&amp;page=1</url>
                        <level>2</level>
                    </submenu>
                    <submenu>
                        <text>热血</text>
                        <url>https://m.zaimanhua.com/api/app/v1/comic/filter/list?status=0&amp;theme=3248&amp;zone=0&amp;sortType=1&amp;size=20&amp;cate=0&amp;page=1</url>
                        <level>2</level>
                    </submenu>
                    <submenu>
                        <text>搞笑</text>
                        <url>https://m.zaimanhua.com/api/app/v1/comic/filter/list?status=0&amp;theme=7568&amp;zone=0&amp;sortType=1&amp;size=20&amp;cate=0&amp;page=1</url>
                        <level>2</level>
                    </submenu>
                    <submenu>
                        <text>科幻</text>
                        <url>https://m.zaimanhua.com/api/app/v1/comic/filter/list?status=0&amp;theme=7&amp;zone=0&amp;sortType=1&amp;size=20&amp;cate=0&amp;page=1</url>
                        <level>2</level>
                    </submenu>
                    <submenu>
                        <text>竞技</text>
                        <url>https://m.zaimanhua.com/api/app/v1/comic/filter/list?status=0&amp;theme=10&amp;zone=0&amp;sortType=1&amp;size=20&amp;cate=0&amp;page=1</url>
                        <level>2</level>
                    </submenu>
                    <submenu>
                        <text>悬疑</text>
                        <url>https://m.zaimanhua.com/api/app/v1/comic/filter/list?status=0&amp;theme=3245&amp;zone=0&amp;sortType=1&amp;size=20&amp;cate=0&amp;page=1</url>
                        <level>2</level>
                    </submenu>
                    <submenu>
                        <text>爱情</text>
                        <url>https://m.zaimanhua.com/api/app/v1/comic/filter/list?status=0&amp;theme=8&amp;zone=0&amp;sortType=1&amp;size=20&amp;cate=0&amp;page=1</url>
                        <level>2</level>
                    </submenu>
                    <submenu>
                        <text>格斗</text>
                        <url>https://m.zaimanhua.com/api/app/v1/comic/filter/list?status=0&amp;theme=6&amp;zone=0&amp;sortType=1&amp;size=20&amp;cate=0&amp;page=1</url>
                        <level>2</level>
                    </submenu>
                    <submenu>
                        <text>校园</text>
                        <url>https://m.zaimanhua.com/api/app/v1/comic/filter/list?status=0&amp;theme=13&amp;zone=0&amp;sortType=1&amp;size=20&amp;cate=0&amp;page=1</url>
                        <level>2</level>
                    </submenu>
                    <submenu>
                        <text>仙侠</text>
                        <url>https://m.zaimanhua.com/api/app/v1/comic/filter/list?status=0&amp;theme=7900&amp;zone=0&amp;sortType=1&amp;size=20&amp;cate=0&amp;page=1</url>
                        <level>2</level>
                    </submenu>
                    <submenu>
                        <text>伪娘</text>
                        <url>https://m.zaimanhua.com/api/app/v1/comic/filter/list?status=0&amp;theme=3244&amp;zone=0&amp;sortType=1&amp;size=20&amp;cate=0&amp;page=1</url>
                        <level>2</level>
                    </submenu>
                    <submenu>
                        <text>冒险</text>
                        <url>https://m.zaimanhua.com/api/app/v1/comic/filter/list?status=0&amp;theme=4&amp;zone=0&amp;sortType=1&amp;size=20&amp;cate=0&amp;page=1</url>
                        <level>2</level>
                    </submenu>
                </subset>
            </menu>
        </menuBar>
        
        <!--模块映射规则-->
        <mapRule>
            <!--第一层模块-->
            <module>
                <level>1</level>
                <css>1</css>
                <widget>1</widget>
                <path>_JSON*0|_Object*data|_Array*999|(_Object*title|_String+_Object*types|_String+_Object*last_update_chapter_name|_String|_TEXT*0|[_REPL_]ゆり*百合,_Object*comic_id|_String|_TEXT*0|[_ADD-L_]*/api/app/v1/comic/detail/|[_ADD-R_]*?_v=15,_Object*cover|_String)</path>
                <tag>iconLinkList</tag>
                <type>2</type>
                <checkText>null</checkText>
                <offset>null</offset>
            </module>
            
            <module>
                <level>1</level>
                <css>1</css>
                <widget>-1</widget>
                <path>SELF</path>
                <tag>currentNumber</tag>
                <type>0</type>
                <checkText>null</checkText>
                <offset>null</offset>
            </module>
            
            <module>
                <level>1</level>
                <css>1</css>
                <widget>-2</widget>
                <path>-1</path>
                <tag>totalNumber</tag>
                <type>0</type>
                <checkText>null</checkText>
                <offset>null</offset>
            </module>
            
            <module>
                <level>1</level>
                <css>1</css>
                <widget>-999</widget>
                <path>JUMP</path>
                <tag>previousPage</tag>
                <type>0</type>
                <checkText>null</checkText>
                <offset>null</offset>
            </module>
            
            <module>
                <level>1</level>
                <css>1</css>
                <widget>-999</widget>
                <path>JUMP</path>
                <tag>nextPage</tag>
                <type>0</type>
                <checkText>null</checkText>
                <offset>null</offset>
            </module>
            
            <module>
                <level>1</level>
                <css>2</css>
                <widget>1</widget>
                <path>_JSON*0|_Object*data|_Object*list|_Array*999|(_Object*title|_String+_Object*status|_String+_Object*last_name|_String,_Object*id|_String|_TEXT*0|[_ADD-L_]*/api/app/v1/comic/detail/|[_ADD-R_]*?_v=15,_Object*cover|_String)</path>
                <tag>iconLinkList</tag>
                <type>2</type>
                <checkText>null</checkText>
                <offset>null</offset>
            </module>
            
            <module>
                <level>1</level>
                <css>2</css>
                <widget>-1</widget>
                <path>null</path>
                <tag>currentNumber</tag>
                <type>0</type>
                <checkText>null</checkText>
                <offset>null</offset>
            </module>
            
            <module>
                <level>1</level>
                <css>2</css>
                <widget>-2</widget>
                <path>null</path>
                <tag>totalNumber</tag>
                <type>0</type>
                <checkText>null</checkText>
                <offset>null</offset>
            </module>
            
            <module>
                <level>1</level>
                <css>2</css>
                <widget>-999</widget>
                <path>null</path>
                <tag>previousPage</tag>
                <type>0</type>
                <checkText>null</checkText>
                <offset>null</offset>
            </module>
            
            <module>
                <level>1</level>
                <css>2</css>
                <widget>-999</widget>
                <path>null</path>
                <tag>nextPage</tag>
                <type>0</type>
                <checkText>null</checkText>
                <offset>null</offset>
            </module>

            <module>
                <level>1</level>
                <css>3</css>
                <widget>1</widget>
                <path>_JSON*0|_Object*data|_Object*comicList|_Array*999|(_Object*name|_String+_Object*status|_String+_Object*last_update_chapter_name|_String,_Object*id|_String|_TEXT*0|[_ADD-L_]*/api/app/v1/comic/detail/|[_ADD-R_]*?_v=15,_Object*cover|_String)</path>
                <tag>iconLinkList</tag>
                <type>2</type>
                <checkText>null</checkText>
                <offset>null</offset>
            </module>
            
            <module>
                <level>1</level>
                <css>3</css>
                <widget>-1</widget>
                <path>SELF</path>
                <tag>currentNumber</tag>
                <type>0</type>
                <checkText>null</checkText>
                <offset>null</offset>
            </module>
            
            <module>
                <level>1</level>
                <css>3</css>
                <widget>-2</widget>
                <path>-1</path>
                <tag>totalNumber</tag>
                <type>0</type>
                <checkText>null</checkText>
                <offset>null</offset>
            </module>
            
            <module>
                <level>1</level>
                <css>3</css>
                <widget>-999</widget>
                <path>JUMP</path>
                <tag>previousPage</tag>
                <type>0</type>
                <checkText>null</checkText>
                <offset>null</offset>
            </module>
            
            <module>
                <level>1</level>
                <css>3</css>
                <widget>-999</widget>
                <path>JUMP</path>
                <tag>nextPage</tag>
                <type>0</type>
                <checkText>null</checkText>
                <offset>null</offset>
            </module>

            <!--第二层模块-->
            <module>
                <level>2</level>
                <css>1</css>
                <widget>2</widget>
                <path>_JSON*0|_Object*data|_Object*data|_Object*title|_String</path>
                <tag>title</tag>
                <type>0</type>
                <checkText>null</checkText>
                <offset>null</offset>
            </module>
            
            <module>
                <level>2</level>
                <css>1</css>
                <widget>3</widget>
                <path>_JSON*0|_Object*data|_Object*data|_Object*cover|_String</path>
                <tag>cover</tag>
                <type>0</type>
                <checkText>null</checkText>
                <offset>null</offset>
            </module>
            
            <module>
                <level>2</level>
                <css>1</css>
                <widget>4</widget>
                <path>_JSON*0|_Object*data|_Object*data|_Object*last_updatetime|_String|_TEXT*0|[_NUM-L_]*|[_ADD-R_]*000|[_MAYBE-MS-TO-DATE_]*|[_ADD-L_]*更新时间：|[_ADD-R_]*#T1#+_JSON*0|_Object*data|_Object*data|_Object*last_update_chapter_name|_String|_TEXT*0|[_ADD-L_]*更新至|[_ADD-R_]*#T1#+_JSON*0|_Object*data|_Object*data|_Object*status|_Array*0|_Object*tag_name|_String|_TEXT*0|[_ADD-L_]*状态：|[_ADD-R_]*#T1#+_JSON*0|_Object*data|_Object*data|_Object*types|_Array*999|(_Object*tag_name|_String)|_TEXT*0|[_REPL_][*|[_REPL_]]*|[_ADD-L_]*标签：|[_ADD-R_]*#T1#+_JSON*0|_Object*data|_Object*data|_Object*description|_String|_TEXT*0|[_ADD-L_]*简介：</path>
                <tag>intro</tag>
                <type>0</type>
                <checkText>null</checkText>
                <offset>null</offset>
            </module>
            
            <module>
                <level>2</level>
                <css>1</css>
                <widget>-999</widget>
                <path>SELF</path>
                <tag>indexWebsite</tag>
                <type>0</type>
                <checkText>null</checkText>
                <offset>_TEXT*0|[_ADD-R_]*/|[_ADD-R_]*{Accept*#U0#Connection*keep-alive#U0#User-Agent*PostmanRuntime#U0#authorization*Bearer eyJhbGciOiJIUzI1NiIsInR5cCI6IkpXVCJ9.eyJhdXRob3JpemVkIjp0cnVlLCJleHAiOjE3NjUxNjkzNDEsImlhdCI6MTc2MjU3NzM0MSwianRpIjoidW5pcXVlX2lkIiwibmJmIjoxNzYyNTc3MzQxLCJzdWIiOiJ6bWhfNDI1MTExIiwidWlkIjo0MjUxMTEsInVzZXJfbGV2ZWwiOjF9.4c9_QylERYaQ0ycpRzMouiBLeeyJn_355l29pgkKOIw}</offset>
            </module>
            
            <module>
                <level>2</level>
                <css>1</css>
                <widget>1</widget>
                <path>_JSON*0|_Object*data|_Object*data|_Object*chapters|_Array*0|_Object*data|_Array*999|(_Object*chapter_title|_String,_Object*chapter_id|_String|_TEXT*0|[_ADD-L_]*./)+_JSON*0|_Object*data|_Object*data|_Object*chapters|_Array*1|_Object*data|_Array*999|(_Object*chapter_title|_String,_Object*chapter_id|_String|_TEXT*0|[_ADD-L_]*./)+_JSON*0|_Object*data|_Object*data|_Object*chapters|_Array*2|_Object*data|_Array*999|(_Object*chapter_title|_String,_Object*chapter_id|_String|_TEXT*0|[_ADD-L_]*./)</path>
                <tag>textLinkList</tag>
                <type>2</type>
                <checkText>null</checkText>
                <offset>null</offset>
            </module>
            
            <!--自定义模块【名字要相互区别，不能够有重复】-->
            <module>
                <level>-1</level>
                <css>1</css>
                <widget>-999</widget>
                <path>null</path>
                <tag>null</tag>
                <type>0</type>
                <checkText>null</checkText>
                <offset>null</offset>
            </module>
        </mapRule>
        
        <!--资源的分布规则-->
        <resRule>
            <resType>img</resType>
            <resPath>null</resPath>
            <imageIncrease>null</imageIncrease>
            <pageIncrease>null</pageIncrease>
            <forceParsing>yes</forceParsing>
            <checkTextPath>null</checkTextPath>
            <checkTextRegular>null</checkTextRegular>
            <hrefPath>null</hrefPath>
            <startFormatParam>null</startFormatParam>
            <endFormatParam>null</endFormatParam>
            <fontError>null</fontError>
            <playManager>null</playManager>
        </resRule>
        
        <!--强制解析规则【可在自定义模块内加入额外参数；如果所有节点均为空，则说明站点不需要强制解析】-->
        <forceParseRule>
            <parseType>html</parseType>
            <device>pc</device>
            <imageInnerHeader>null</imageInnerHeader>
            <urlFormatParam>_TEXT*0|[_REPL_]/detail/*/chapter/|[_REPL_]?_v=15*|[_ADD-R_]*{Accept*#U0#Connection*keep-alive#U0#User-Agent*PostmanRuntime#U0#authorization*Bearer eyJhbGciOiJIUzI1NiIsInR5cCI6IkpXVCJ9.eyJhdXRob3JpemVkIjp0cnVlLCJleHAiOjE3NjUxNjkzNDEsImlhdCI6MTc2MjU3NzM0MSwianRpIjoidW5pcXVlX2lkIiwibmJmIjoxNzYyNTc3MzQxLCJzdWIiOiJ6bWhfNDI1MTExIiwidWlkIjo0MjUxMTEsInVzZXJfbGV2ZWwiOjF9.4c9_QylERYaQ0ycpRzMouiBLeeyJn_355l29pgkKOIw}</urlFormatParam>
            <imageFormatParam>null</imageFormatParam>
            <dataFormatParam>null</dataFormatParam>
            <runJS>null</runJS>
            <imageType>static</imageType>
            <number>null</number>
            <pagePath>null</pagePath>
            <resPath>_JSON*0|_Object*data|_Object*data|_Object*page_url_hd|_Array*999|(_String)</resPath>
            <resFormatParam>null</resFormatParam>
            <xhrRegular>null</xhrRegular>
            <scriptRegular>null</scriptRegular>
            <imageRegular>null</imageRegular>
        </forceParseRule>
    </resolver>
</resolvers>